semeio/__init__.py
semeio/version.py
semeio/_docs_utils/__init__.py
semeio/_docs_utils/_json_schema_2_rst.py
semeio/_exceptions/__init__.py
semeio/_exceptions/exceptions.py
semeio/fmudesign/__init__.py
semeio/fmudesign/_designsummary.py
semeio/fmudesign/_excel_to_dict.py
semeio/fmudesign/config_validation.py
semeio/fmudesign/create_design.py
semeio/fmudesign/design_distributions.py
semeio/fmudesign/fmudesignrunner.py
semeio/fmudesign/quality_report.py
semeio/fmudesign/utils.py
semeio/fmudesign/examples/ex1_onebyone_rms_repeat.xlsx
semeio/fmudesign/examples/ex2_correlations.xlsx
semeio/fmudesign/examples/ex2_doe1.xlsx
semeio/fmudesign/examples/ex3_velocities.xlsx
semeio/fmudesign/examples/ex4_background_parameters.xlsx
semeio/fmudesign/examples/ex4_doe1.xlsx
semeio/fmudesign/examples/ex5_single_reference.xlsx
semeio/fmudesign/examples/ex6_singlereference_and_seed.xlsx
semeio/fmudesign/examples/ex7_background_no_seed.xlsx
semeio/fmudesign/examples/ex7_doe1.xlsx
semeio/fmudesign/examples/ex8_mc_with_correls.xlsx
semeio/fmudesign/examples/fmudesign_ex_montecarlo.xlsx
semeio/fmudesign/examples/fmudesign_ex_onebyone.xlsx
semeio/forward_models/__init__.py
semeio/forward_models/design2params/__init__.py
semeio/forward_models/design2params/design2params.py
semeio/forward_models/design_kw/__init__.py
semeio/forward_models/design_kw/design_kw.py
semeio/forward_models/overburden_timeshift/__init__.py
semeio/forward_models/overburden_timeshift/ots.py
semeio/forward_models/overburden_timeshift/ots_config.py
semeio/forward_models/overburden_timeshift/ots_res_surface.py
semeio/forward_models/overburden_timeshift/ots_vel_surface.py
semeio/forward_models/rft/__init__.py
semeio/forward_models/rft/gendata_rft.py
semeio/forward_models/rft/trajectory.py
semeio/forward_models/rft/utility.py
semeio/forward_models/rft/zonemap.py
semeio/forward_models/scripts/__init__.py
semeio/forward_models/scripts/design2params.py
semeio/forward_models/scripts/design_kw.py
semeio-3.1.3.dist-info/licenses/LICENSE
semeio-3.1.3.dist-info/METADATA
semeio-3.1.3.dist-info/WHEEL
semeio-3.1.3.dist-info/entry_points.txt
semeio-3.1.3.dist-info/top_level.txt
semeio-3.1.3.dist-info/RECORD
