Metadata-Version: 2.4
Name: semeio
Version: 3.1.3
Summary: Forward models and workflows for Ert.
Author-email: Equinor ASA <fg_sib-scout@equinor.com>
License-Expression: GPL-3.0-or-later
Project-URL: repository, https://github.com/equinor/semeio
Classifier: Environment :: Plugins
Classifier: Intended Audience :: Developers
Classifier: Intended Audience :: Science/Research
Classifier: Natural Language :: English
Classifier: Programming Language :: Python
Classifier: Programming Language :: Python :: 3.11
Classifier: Programming Language :: Python :: 3.12
Classifier: Programming Language :: Python :: 3.13
Classifier: Topic :: Scientific/Engineering
Classifier: Topic :: Software Development :: Libraries :: Python Modules
Requires-Python: >=3.11
License-File: LICENSE
Requires-Dist: cvxpy
Requires-Dist: ert>=17.0.0
Requires-Dist: fmu-ensemble>1.6.5
Requires-Dist: importlib_metadata
Requires-Dist: importlib_resources
Requires-Dist: numpy
Requires-Dist: pandas>1.3.0
Requires-Dist: pydantic>=2.9
Requires-Dist: pyscal>=0.4.0
Requires-Dist: resdata
Requires-Dist: scikit-learn
Requires-Dist: scipy
Requires-Dist: segyio
Requires-Dist: xlrd
Requires-Dist: xtgeo>=2.15
Requires-Dist: seaborn
Requires-Dist: probabilit>=0.4.0
Requires-Dist: resfo-utilities>=0.1.1
Provides-Extra: test
Requires-Dist: hypothesis; extra == "test"
Requires-Dist: odfpy; extra == "test"
Requires-Dist: oil_reservoir_synthesizer; extra == "test"
Requires-Dist: openpyxl; extra == "test"
Requires-Dist: pytest; extra == "test"
Requires-Dist: pytest-console-scripts; extra == "test"
Requires-Dist: pytest-snapshot; extra == "test"
Requires-Dist: pytest-xdist; extra == "test"
Requires-Dist: rstcheck-core; extra == "test"
Requires-Dist: xlwt; extra == "test"
Provides-Extra: style
Requires-Dist: pre-commit; extra == "style"
Provides-Extra: types
Requires-Dist: mypy; extra == "types"
Requires-Dist: pandas-stubs; extra == "types"
Requires-Dist: types-PyYAML; extra == "types"
Requires-Dist: types-openpyxl; extra == "types"
Requires-Dist: types-setuptools; extra == "types"
Requires-Dist: types-seaborn; extra == "types"
Dynamic: license-file
